{"scopes":{"CNTY":{"PRSD":{"1":{"candidates":[{"id":"P1-P","candidate":"GEORGE-NICOLAE SIMION","party":null,"votes":73172},{"id":"P2-P","candidate":"NICUȘOR-DANIEL DAN","party":null,"votes":73946}],"info":{"precincts_with_data":405,"precincts":440}},"2":{"candidates":[{"id":"P1-P","candidate":"GEORGE-NICOLAE SIMION","party":null,"votes":102379},{"id":"P2-P","candidate":"NICUȘOR-DANIEL DAN","party":null,"votes":92245}],"info":{"precincts_with_data":429,"precincts":440}},"3":{"candidates":[{"id":"P1-P","candidate":"GEORGE-NICOLAE SIMION","party":null,"votes":143516},{"id":"P2-P","candidate":"NICUȘOR-DANIEL DAN","party":null,"votes":122241}],"info":{"precincts_with_data":485,"precincts":527}},"4":{"candidates":[{"id":"P1-P","candidate":"GEORGE-NICOLAE SIMION","party":null,"votes":135997},{"id":"P2-P","candidate":"NICUȘOR-DANIEL DAN","party":null,"votes":128867}],"info":{"precincts_with_data":630,"precincts":640}},"5":{"candidates":[{"id":"P1-P","candidate":"GEORGE-NICOLAE SIMION","party":null,"votes":83510},{"id":"P2-P","candidate":"NICUȘOR-DANIEL DAN","party":null,"votes":136915}],"info":{"precincts_with_data":578,"precincts":660}},"6":{"candidates":[{"id":"P1-P","candidate":"GEORGE-NICOLAE SIMION","party":null,"votes":47529},{"id":"P2-P","candidate":"NICUȘOR-DANIEL DAN","party":null,"votes":41321}],"info":{"precincts_with_data":249,"precincts":314}},"7":{"candidates":[{"id":"P1-P","candidate":"GEORGE-NICOLAE SIMION","party":null,"votes":85238},{"id":"P2-P","candidate":"NICUȘOR-DANIEL DAN","party":null,"votes":71216}],"info":{"precincts_with_data":428,"precincts":434}},"8":{"candidates":[{"id":"P1-P","candidate":"GEORGE-NICOLAE SIMION","party":null,"votes":87283},{"id":"P2-P","candidate":"NICUȘOR-DANIEL DAN","party":null,"votes":135548}],"info":{"precincts_with_data":365,"precincts":468}},"9":{"candidates":[{"id":"P1-P","candidate":"GEORGE-NICOLAE SIMION","party":null,"votes":70301},{"id":"P2-P","candidate":"NICUȘOR-DANIEL DAN","party":null,"votes":58435}],"info":{"precincts_with_data":269,"precincts":284}},"10":{"candidates":[{"id":"P1-P","candidate":"GEORGE-NICOLAE SIMION","party":null,"votes":91551},{"id":"P2-P","candidate":"NICUȘOR-DANIEL DAN","party":null,"votes":88808}],"info":{"precincts_with_data":398,"precincts":425}},"11":{"candidates":[{"id":"P1-P","candidate":"GEORGE-NICOLAE SIMION","party":null,"votes":61611},{"id":"P2-P","candidate":"NICUȘOR-DANIEL DAN","party":null,"votes":44725}],"info":{"precincts_with_data":348,"precincts":364}},"12":{"candidates":[{"id":"P1-P","candidate":"GEORGE-NICOLAE SIMION","party":null,"votes":65905},{"id":"P2-P","candidate":"NICUȘOR-DANIEL DAN","party":null,"votes":48026}],"info":{"precincts_with_data":209,"precincts":235}},"13":{"candidates":[{"id":"P1-P","candidate":"GEORGE-NICOLAE SIMION","party":null,"votes":83652},{"id":"P2-P","candidate":"NICUȘOR-DANIEL DAN","party":null,"votes":145632}],"info":{"precincts_with_data":505,"precincts":674}},"14":{"candidates":[{"id":"P1-P","candidate":"GEORGE-NICOLAE SIMION","party":null,"votes":150862},{"id":"P2-P","candidate":"NICUȘOR-DANIEL DAN","party":null,"votes":149321}],"info":{"precincts_with_data":503,"precincts":563}},"15":{"candidates":[{"id":"P1-P","candidate":"GEORGE-NICOLAE SIMION","party":null,"votes":14430},{"id":"P2-P","candidate":"NICUȘOR-DANIEL DAN","party":null,"votes":77026}],"info":{"precincts_with_data":202,"precincts":214}},"16":{"candidates":[{"id":"P1-P","candidate":"GEORGE-NICOLAE SIMION","party":null,"votes":117000},{"id":"P2-P","candidate":"NICUȘOR-DANIEL DAN","party":null,"votes":96819}],"info":{"precincts_with_data":408,"precincts":434}},"17":{"candidates":[{"id":"P1-P","candidate":"GEORGE-NICOLAE SIMION","party":null,"votes":124948},{"id":"P2-P","candidate":"NICUȘOR-DANIEL DAN","party":null,"votes":123618}],"info":{"precincts_with_data":482,"precincts":534}},"18":{"candidates":[{"id":"P1-P","candidate":"GEORGE-NICOLAE SIMION","party":null,"votes":103409},{"id":"P2-P","candidate":"NICUȘOR-DANIEL DAN","party":null,"votes":111745}],"info":{"precincts_with_data":398,"precincts":438}},"19":{"candidates":[{"id":"P1-P","candidate":"GEORGE-NICOLAE SIMION","party":null,"votes":67772},{"id":"P2-P","candidate":"NICUȘOR-DANIEL DAN","party":null,"votes":51126}],"info":{"precincts_with_data":224,"precincts":245}},"20":{"candidates":[{"id":"P1-P","candidate":"GEORGE-NICOLAE SIMION","party":null,"votes":74461},{"id":"P2-P","candidate":"NICUȘOR-DANIEL DAN","party":null,"votes":44426}],"info":{"precincts_with_data":281,"precincts":334}},"21":{"candidates":[{"id":"P1-P","candidate":"GEORGE-NICOLAE SIMION","party":null,"votes":14100},{"id":"P2-P","candidate":"NICUȘOR-DANIEL DAN","party":null,"votes":137021}],"info":{"precincts_with_data":285,"precincts":292}},"22":{"candidates":[{"id":"P1-P","candidate":"GEORGE-NICOLAE SIMION","party":null,"votes":92376},{"id":"P2-P","candidate":"NICUȘOR-DANIEL DAN","party":null,"votes":77107}],"info":{"precincts_with_data":497,"precincts":525}},"23":{"candidates":[{"id":"P1-P","candidate":"GEORGE-NICOLAE SIMION","party":null,"votes":59313},{"id":"P2-P","candidate":"NICUȘOR-DANIEL DAN","party":null,"votes":46724}],"info":{"precincts_with_data":211,"precincts":220}},"24":{"candidates":[{"id":"P1-P","candidate":"GEORGE-NICOLAE SIMION","party":null,"votes":144371},{"id":"P2-P","candidate":"NICUȘOR-DANIEL DAN","party":null,"votes":191411}],"info":{"precincts_with_data":716,"precincts":784}},"25":{"candidates":[{"id":"P1-P","candidate":"GEORGE-NICOLAE SIMION","party":null,"votes":41860},{"id":"P2-P","candidate":"NICUȘOR-DANIEL DAN","party":null,"votes":40260}],"info":{"precincts_with_data":88,"precincts":296}},"26":{"candidates":[{"id":"P1-P","candidate":"GEORGE-NICOLAE SIMION","party":null,"votes":90355},{"id":"P2-P","candidate":"NICUȘOR-DANIEL DAN","party":null,"votes":92653}],"info":{"precincts_with_data":420,"precincts":444}},"27":{"candidates":[{"id":"P1-P","candidate":"GEORGE-NICOLAE SIMION","party":null,"votes":58418},{"id":"P2-P","candidate":"NICUȘOR-DANIEL DAN","party":null,"votes":45784}],"info":{"precincts_with_data":273,"precincts":290}},"28":{"candidates":[{"id":"P1-P","candidate":"GEORGE-NICOLAE SIMION","party":null,"votes":75530},{"id":"P2-P","candidate":"NICUȘOR-DANIEL DAN","party":null,"votes":147897}],"info":{"precincts_with_data":534,"precincts":572}},"29":{"candidates":[{"id":"P1-P","candidate":"GEORGE-NICOLAE SIMION","party":null,"votes":108971},{"id":"P2-P","candidate":"NICUȘOR-DANIEL DAN","party":null,"votes":97014}],"info":{"precincts_with_data":476,"precincts":490}},"30":{"candidates":[{"id":"P1-P","candidate":"GEORGE-NICOLAE SIMION","party":null,"votes":87976},{"id":"P2-P","candidate":"NICUȘOR-DANIEL DAN","party":null,"votes":65468}],"info":{"precincts_with_data":328,"precincts":381}},"31":{"candidates":[{"id":"P1-P","candidate":"GEORGE-NICOLAE SIMION","party":null,"votes":166764},{"id":"P2-P","candidate":"NICUȘOR-DANIEL DAN","party":null,"votes":181744}],"info":{"precincts_with_data":587,"precincts":624}},"32":{"candidates":[{"id":"P1-P","candidate":"GEORGE-NICOLAE SIMION","party":null,"votes":48901},{"id":"P2-P","candidate":"NICUȘOR-DANIEL DAN","party":null,"votes":85038}],"info":{"precincts_with_data":329,"precincts":340}},"33":{"candidates":[{"id":"P1-P","candidate":"GEORGE-NICOLAE SIMION","party":null,"votes":36539},{"id":"P2-P","candidate":"NICUȘOR-DANIEL DAN","party":null,"votes":57232}],"info":{"precincts_with_data":294,"precincts":312}},"34":{"candidates":[{"id":"P1-P","candidate":"GEORGE-NICOLAE SIMION","party":null,"votes":75736},{"id":"P2-P","candidate":"NICUȘOR-DANIEL DAN","party":null,"votes":95687}],"info":{"precincts_with_data":335,"precincts":381}},"35":{"candidates":[{"id":"P1-P","candidate":"GEORGE-NICOLAE SIMION","party":null,"votes":156023},{"id":"P2-P","candidate":"NICUȘOR-DANIEL DAN","party":null,"votes":111815}],"info":{"precincts_with_data":534,"precincts":564}},"36":{"candidates":[{"id":"P1-P","candidate":"GEORGE-NICOLAE SIMION","party":null,"votes":74220},{"id":"P2-P","candidate":"NICUȘOR-DANIEL DAN","party":null,"votes":63067}],"info":{"precincts_with_data":317,"precincts":334}},"37":{"candidates":[{"id":"P1-P","candidate":"GEORGE-NICOLAE SIMION","party":null,"votes":131742},{"id":"P2-P","candidate":"NICUȘOR-DANIEL DAN","party":null,"votes":173952}],"info":{"precincts_with_data":554,"precincts":619}},"38":{"candidates":[{"id":"P1-P","candidate":"GEORGE-NICOLAE SIMION","party":null,"votes":47654},{"id":"P2-P","candidate":"NICUȘOR-DANIEL DAN","party":null,"votes":33370}],"info":{"precincts_with_data":184,"precincts":205}},"39":{"candidates":[{"id":"P1-P","candidate":"GEORGE-NICOLAE SIMION","party":null,"votes":73961},{"id":"P2-P","candidate":"NICUȘOR-DANIEL DAN","party":null,"votes":68623}],"info":{"precincts_with_data":529,"precincts":552}},"40":{"candidates":[{"id":"P1-P","candidate":"GEORGE-NICOLAE SIMION","party":null,"votes":90181},{"id":"P2-P","candidate":"NICUȘOR-DANIEL DAN","party":null,"votes":76685}],"info":{"precincts_with_data":423,"precincts":434}},"41":{"candidates":[{"id":"P1-P","candidate":"GEORGE-NICOLAE SIMION","party":null,"votes":66834},{"id":"P2-P","candidate":"NICUȘOR-DANIEL DAN","party":null,"votes":56916}],"info":{"precincts_with_data":321,"precincts":364}},"42":{"candidates":[{"id":"P1-P","candidate":"GEORGE-NICOLAE SIMION","party":null,"votes":222169},{"id":"P2-P","candidate":"NICUȘOR-DANIEL DAN","party":null,"votes":483401}],"info":{"precincts_with_data":904,"precincts":1289}},"43":{"candidates":[{"id":"P1-P","candidate":"GEORGE-NICOLAE SIMION","party":null,"votes":42822},{"id":"P2-P","candidate":"NICUȘOR-DANIEL DAN","party":null,"votes":39703}],"info":{"precincts_with_data":166,"precincts":965}},"44":{"candidates":[{"id":"P1-P","candidate":"GEORGE-NICOLAE SIMION","party":null,"votes":17175},{"id":"P2-P","candidate":"NICUȘOR-DANIEL DAN","party":null,"votes":39777}],"info":{"precincts_with_data":70,"precincts":166}},"45":{"candidates":[{"id":"P1-P","candidate":"GEORGE-NICOLAE SIMION","party":null,"votes":40082},{"id":"P2-P","candidate":"NICUȘOR-DANIEL DAN","party":null,"votes":87068}],"info":{"precincts_with_data":145,"precincts":202}},"46":{"candidates":[{"id":"P1-P","candidate":"GEORGE-NICOLAE SIMION","party":null,"votes":52145},{"id":"P2-P","candidate":"NICUȘOR-DANIEL DAN","party":null,"votes":126773}],"info":{"precincts_with_data":248,"precincts":294}},"47":{"candidates":[{"id":"P1-P","candidate":"GEORGE-NICOLAE SIMION","party":null,"votes":38328},{"id":"P2-P","candidate":"NICUȘOR-DANIEL DAN","party":null,"votes":77768}],"info":{"precincts_with_data":137,"precincts":189}},"48":{"candidates":[{"id":"P1-P","candidate":"GEORGE-NICOLAE SIMION","party":null,"votes":38423},{"id":"P2-P","candidate":"NICUȘOR-DANIEL DAN","party":null,"votes":59236}],"info":{"precincts_with_data":148,"precincts":198}},"49":{"candidates":[{"id":"P1-P","candidate":"GEORGE-NICOLAE SIMION","party":null,"votes":36016},{"id":"P2-P","candidate":"NICUȘOR-DANIEL DAN","party":null,"votes":92779}],"info":{"precincts_with_data":156,"precincts":240}}},"PRSD_C":{"43":{"candidates":[{"id":"P1-P","candidate":"GEORGE-NICOLAE SIMION","party":null,"votes":7},{"id":"P2-P","candidate":"NICUȘOR-DANIEL DAN","party":null,"votes":44}],"info":{"precincts_with_data":73,"precincts":141}}}},"CNTRY":{"PRSD":{"RO":{"candidates":[{"id":"P1-P","candidate":"GEORGE-NICOLAE SIMION","party":null,"votes":3791342},{"id":"P2-P","candidate":"NICUȘOR-DANIEL DAN","party":null,"votes":4310578}],"info":{"precincts_with_data":17101,"precincts":19944}}},"PRSD_C":{"RO":{"candidates":[{"id":"P1-P","candidate":"GEORGE-NICOLAE SIMION","party":null,"votes":7},{"id":"P2-P","candidate":"NICUȘOR-DANIEL DAN","party":null,"votes":44}],"info":{"precincts_with_data":73,"precincts":141}}}}}}