{"scopes":{"CNTY":{"PRSD":{"1":{"candidates":[{"id":"P1-P","candidate":"GEORGE-NICOLAE SIMION","party":null,"votes":16798},{"id":"P2-P","candidate":"NICUȘOR-DANIEL DAN","party":null,"votes":14165}],"info":{"precincts_with_data":167,"precincts":440}},"2":{"candidates":[{"id":"P1-P","candidate":"GEORGE-NICOLAE SIMION","party":null,"votes":24151},{"id":"P2-P","candidate":"NICUȘOR-DANIEL DAN","party":null,"votes":18784}],"info":{"precincts_with_data":174,"precincts":440}},"3":{"candidates":[{"id":"P1-P","candidate":"GEORGE-NICOLAE SIMION","party":null,"votes":35396},{"id":"P2-P","candidate":"NICUȘOR-DANIEL DAN","party":null,"votes":24406}],"info":{"precincts_with_data":166,"precincts":527}},"4":{"candidates":[{"id":"P1-P","candidate":"GEORGE-NICOLAE SIMION","party":null,"votes":46976},{"id":"P2-P","candidate":"NICUȘOR-DANIEL DAN","party":null,"votes":39877}],"info":{"precincts_with_data":272,"precincts":640}},"5":{"candidates":[{"id":"P1-P","candidate":"GEORGE-NICOLAE SIMION","party":null,"votes":21571},{"id":"P2-P","candidate":"NICUȘOR-DANIEL DAN","party":null,"votes":26546}],"info":{"precincts_with_data":210,"precincts":660}},"6":{"candidates":[{"id":"P1-P","candidate":"GEORGE-NICOLAE SIMION","party":null,"votes":9351},{"id":"P2-P","candidate":"NICUȘOR-DANIEL DAN","party":null,"votes":6954}],"info":{"precincts_with_data":84,"precincts":314}},"7":{"candidates":[{"id":"P1-P","candidate":"GEORGE-NICOLAE SIMION","party":null,"votes":47316},{"id":"P2-P","candidate":"NICUȘOR-DANIEL DAN","party":null,"votes":36302}],"info":{"precincts_with_data":273,"precincts":434}},"8":{"candidates":[{"id":"P1-P","candidate":"GEORGE-NICOLAE SIMION","party":null,"votes":8280},{"id":"P2-P","candidate":"NICUȘOR-DANIEL DAN","party":null,"votes":9738}],"info":{"precincts_with_data":57,"precincts":468}},"9":{"candidates":[{"id":"P1-P","candidate":"GEORGE-NICOLAE SIMION","party":null,"votes":29264},{"id":"P2-P","candidate":"NICUȘOR-DANIEL DAN","party":null,"votes":25429}],"info":{"precincts_with_data":126,"precincts":284}},"10":{"candidates":[{"id":"P1-P","candidate":"GEORGE-NICOLAE SIMION","party":null,"votes":25192},{"id":"P2-P","candidate":"NICUȘOR-DANIEL DAN","party":null,"votes":21466}],"info":{"precincts_with_data":164,"precincts":425}},"11":{"candidates":[{"id":"P1-P","candidate":"GEORGE-NICOLAE SIMION","party":null,"votes":18883},{"id":"P2-P","candidate":"NICUȘOR-DANIEL DAN","party":null,"votes":12316}],"info":{"precincts_with_data":145,"precincts":364}},"12":{"candidates":[{"id":"P1-P","candidate":"GEORGE-NICOLAE SIMION","party":null,"votes":6725},{"id":"P2-P","candidate":"NICUȘOR-DANIEL DAN","party":null,"votes":5205}],"info":{"precincts_with_data":31,"precincts":235}},"13":{"candidates":[{"id":"P1-P","candidate":"GEORGE-NICOLAE SIMION","party":null,"votes":19009},{"id":"P2-P","candidate":"NICUȘOR-DANIEL DAN","party":null,"votes":22123}],"info":{"precincts_with_data":215,"precincts":674}},"14":{"candidates":[{"id":"P1-P","candidate":"GEORGE-NICOLAE SIMION","party":null,"votes":30712},{"id":"P2-P","candidate":"NICUȘOR-DANIEL DAN","party":null,"votes":26799}],"info":{"precincts_with_data":153,"precincts":563}},"15":{"candidates":[{"id":"P1-P","candidate":"GEORGE-NICOLAE SIMION","party":null,"votes":3242},{"id":"P2-P","candidate":"NICUȘOR-DANIEL DAN","party":null,"votes":22638}],"info":{"precincts_with_data":78,"precincts":214}},"16":{"candidates":[{"id":"P1-P","candidate":"GEORGE-NICOLAE SIMION","party":null,"votes":34087},{"id":"P2-P","candidate":"NICUȘOR-DANIEL DAN","party":null,"votes":25724}],"info":{"precincts_with_data":143,"precincts":434}},"17":{"candidates":[{"id":"P1-P","candidate":"GEORGE-NICOLAE SIMION","party":null,"votes":34446},{"id":"P2-P","candidate":"NICUȘOR-DANIEL DAN","party":null,"votes":25742}],"info":{"precincts_with_data":189,"precincts":534}},"18":{"candidates":[{"id":"P1-P","candidate":"GEORGE-NICOLAE SIMION","party":null,"votes":12659},{"id":"P2-P","candidate":"NICUȘOR-DANIEL DAN","party":null,"votes":12360}],"info":{"precincts_with_data":68,"precincts":438}},"19":{"candidates":[{"id":"P1-P","candidate":"GEORGE-NICOLAE SIMION","party":null,"votes":11340},{"id":"P2-P","candidate":"NICUȘOR-DANIEL DAN","party":null,"votes":8272}],"info":{"precincts_with_data":57,"precincts":245}},"20":{"candidates":[{"id":"P1-P","candidate":"GEORGE-NICOLAE SIMION","party":null,"votes":12265},{"id":"P2-P","candidate":"NICUȘOR-DANIEL DAN","party":null,"votes":6479}],"info":{"precincts_with_data":68,"precincts":334}},"21":{"candidates":[{"id":"P1-P","candidate":"GEORGE-NICOLAE SIMION","party":null,"votes":6402},{"id":"P2-P","candidate":"NICUȘOR-DANIEL DAN","party":null,"votes":67454}],"info":{"precincts_with_data":173,"precincts":292}},"22":{"candidates":[{"id":"P1-P","candidate":"GEORGE-NICOLAE SIMION","party":null,"votes":35849},{"id":"P2-P","candidate":"NICUȘOR-DANIEL DAN","party":null,"votes":25462}],"info":{"precincts_with_data":293,"precincts":525}},"23":{"candidates":[{"id":"P1-P","candidate":"GEORGE-NICOLAE SIMION","party":null,"votes":13247},{"id":"P2-P","candidate":"NICUȘOR-DANIEL DAN","party":null,"votes":9893}],"info":{"precincts_with_data":59,"precincts":220}},"24":{"candidates":[{"id":"P1-P","candidate":"GEORGE-NICOLAE SIMION","party":null,"votes":44374},{"id":"P2-P","candidate":"NICUȘOR-DANIEL DAN","party":null,"votes":40728}],"info":{"precincts_with_data":281,"precincts":784}},"25":{"candidates":[{"id":"P1-P","candidate":"GEORGE-NICOLAE SIMION","party":null,"votes":357},{"id":"P2-P","candidate":"NICUȘOR-DANIEL DAN","party":null,"votes":228}],"info":{"precincts_with_data":1,"precincts":296}},"26":{"candidates":[{"id":"P1-P","candidate":"GEORGE-NICOLAE SIMION","party":null,"votes":23226},{"id":"P2-P","candidate":"NICUȘOR-DANIEL DAN","party":null,"votes":22757}],"info":{"precincts_with_data":159,"precincts":444}},"27":{"candidates":[{"id":"P1-P","candidate":"GEORGE-NICOLAE SIMION","party":null,"votes":16402},{"id":"P2-P","candidate":"NICUȘOR-DANIEL DAN","party":null,"votes":11225}],"info":{"precincts_with_data":111,"precincts":290}},"28":{"candidates":[{"id":"P1-P","candidate":"GEORGE-NICOLAE SIMION","party":null,"votes":20380},{"id":"P2-P","candidate":"NICUȘOR-DANIEL DAN","party":null,"votes":38671}],"info":{"precincts_with_data":230,"precincts":572}},"29":{"candidates":[{"id":"P1-P","candidate":"GEORGE-NICOLAE SIMION","party":null,"votes":39958},{"id":"P2-P","candidate":"NICUȘOR-DANIEL DAN","party":null,"votes":29819}],"info":{"precincts_with_data":225,"precincts":490}},"30":{"candidates":[{"id":"P1-P","candidate":"GEORGE-NICOLAE SIMION","party":null,"votes":16443},{"id":"P2-P","candidate":"NICUȘOR-DANIEL DAN","party":null,"votes":10287}],"info":{"precincts_with_data":82,"precincts":381}},"31":{"candidates":[{"id":"P1-P","candidate":"GEORGE-NICOLAE SIMION","party":null,"votes":40753},{"id":"P2-P","candidate":"NICUȘOR-DANIEL DAN","party":null,"votes":39146}],"info":{"precincts_with_data":174,"precincts":624}},"32":{"candidates":[{"id":"P1-P","candidate":"GEORGE-NICOLAE SIMION","party":null,"votes":23693},{"id":"P2-P","candidate":"NICUȘOR-DANIEL DAN","party":null,"votes":32722}],"info":{"precincts_with_data":191,"precincts":340}},"33":{"candidates":[{"id":"P1-P","candidate":"GEORGE-NICOLAE SIMION","party":null,"votes":16038},{"id":"P2-P","candidate":"NICUȘOR-DANIEL DAN","party":null,"votes":23244}],"info":{"precincts_with_data":195,"precincts":312}},"34":{"candidates":[{"id":"P1-P","candidate":"GEORGE-NICOLAE SIMION","party":null,"votes":17700},{"id":"P2-P","candidate":"NICUȘOR-DANIEL DAN","party":null,"votes":15101}],"info":{"precincts_with_data":114,"precincts":381}},"35":{"candidates":[{"id":"P1-P","candidate":"GEORGE-NICOLAE SIMION","party":null,"votes":39685},{"id":"P2-P","candidate":"NICUȘOR-DANIEL DAN","party":null,"votes":23490}],"info":{"precincts_with_data":194,"precincts":564}},"36":{"candidates":[{"id":"P1-P","candidate":"GEORGE-NICOLAE SIMION","party":null,"votes":16950},{"id":"P2-P","candidate":"NICUȘOR-DANIEL DAN","party":null,"votes":12869}],"info":{"precincts_with_data":95,"precincts":334}},"37":{"candidates":[{"id":"P1-P","candidate":"GEORGE-NICOLAE SIMION","party":null,"votes":35547},{"id":"P2-P","candidate":"NICUȘOR-DANIEL DAN","party":null,"votes":35302}],"info":{"precincts_with_data":211,"precincts":619}},"38":{"candidates":[{"id":"P1-P","candidate":"GEORGE-NICOLAE SIMION","party":null,"votes":7875},{"id":"P2-P","candidate":"NICUȘOR-DANIEL DAN","party":null,"votes":4086}],"info":{"precincts_with_data":59,"precincts":205}},"39":{"candidates":[{"id":"P1-P","candidate":"GEORGE-NICOLAE SIMION","party":null,"votes":26558},{"id":"P2-P","candidate":"NICUȘOR-DANIEL DAN","party":null,"votes":20610}],"info":{"precincts_with_data":290,"precincts":552}},"40":{"candidates":[{"id":"P1-P","candidate":"GEORGE-NICOLAE SIMION","party":null,"votes":42911},{"id":"P2-P","candidate":"NICUȘOR-DANIEL DAN","party":null,"votes":33565}],"info":{"precincts_with_data":248,"precincts":434}},"41":{"candidates":[{"id":"P1-P","candidate":"GEORGE-NICOLAE SIMION","party":null,"votes":12279},{"id":"P2-P","candidate":"NICUȘOR-DANIEL DAN","party":null,"votes":8229}],"info":{"precincts_with_data":95,"precincts":364}},"42":{"candidates":[{"id":"P1-P","candidate":"GEORGE-NICOLAE SIMION","party":null,"votes":19749},{"id":"P2-P","candidate":"NICUȘOR-DANIEL DAN","party":null,"votes":39102}],"info":{"precincts_with_data":106,"precincts":1289}},"43":{"candidates":[{"id":"P1-P","candidate":"GEORGE-NICOLAE SIMION","party":null,"votes":1274},{"id":"P2-P","candidate":"NICUȘOR-DANIEL DAN","party":null,"votes":6058}],"info":{"precincts_with_data":44,"precincts":965}},"44":{"candidates":[{"id":"P1-P","candidate":"GEORGE-NICOLAE SIMION","party":null,"votes":636},{"id":"P2-P","candidate":"NICUȘOR-DANIEL DAN","party":null,"votes":1703}],"info":{"precincts_with_data":3,"precincts":166}},"45":{"candidates":[{"id":"P1-P","candidate":"GEORGE-NICOLAE SIMION","party":null,"votes":2299},{"id":"P2-P","candidate":"NICUȘOR-DANIEL DAN","party":null,"votes":4224}],"info":{"precincts_with_data":7,"precincts":202}},"46":{"candidates":[{"id":"P1-P","candidate":"GEORGE-NICOLAE SIMION","party":null,"votes":8497},{"id":"P2-P","candidate":"NICUȘOR-DANIEL DAN","party":null,"votes":16406}],"info":{"precincts_with_data":58,"precincts":294}},"47":{"candidates":[{"id":"P1-P","candidate":"GEORGE-NICOLAE SIMION","party":null,"votes":2734},{"id":"P2-P","candidate":"NICUȘOR-DANIEL DAN","party":null,"votes":5905}],"info":{"precincts_with_data":12,"precincts":189}},"48":{"candidates":[{"id":"P1-P","candidate":"GEORGE-NICOLAE SIMION","party":null,"votes":2837},{"id":"P2-P","candidate":"NICUȘOR-DANIEL DAN","party":null,"votes":4430}],"info":{"precincts_with_data":13,"precincts":198}},"49":{"candidates":[{"id":"P1-P","candidate":"GEORGE-NICOLAE SIMION","party":null,"votes":2746},{"id":"P2-P","candidate":"NICUȘOR-DANIEL DAN","party":null,"votes":6434}],"info":{"precincts_with_data":13,"precincts":240}}},"PRSD_C":{"43":{"candidates":[{"id":"P1-P","candidate":"GEORGE-NICOLAE SIMION","party":null,"votes":1},{"id":"P2-P","candidate":"NICUȘOR-DANIEL DAN","party":null,"votes":31}],"info":{"precincts_with_data":36,"precincts":141}}}},"CNTRY":{"PRSD":{"RO":{"candidates":[{"id":"P1-P","candidate":"GEORGE-NICOLAE SIMION","party":null,"votes":965313},{"id":"P2-P","candidate":"NICUȘOR-DANIEL DAN","party":null,"votes":941373}],"info":{"precincts_with_data":6470,"precincts":19944}}},"PRSD_C":{"RO":{"candidates":[{"id":"P1-P","candidate":"GEORGE-NICOLAE SIMION","party":null,"votes":1},{"id":"P2-P","candidate":"NICUȘOR-DANIEL DAN","party":null,"votes":31}],"info":{"precincts_with_data":36,"precincts":141}}}}}}