{"county":[{"initial_count_lp":302142,"initial_count_lc":0,"precincts_count":440,"LP":134692,"LS":19471,"LSC":0,"UM":2166,"LT":156329,"presence":51.7402,"age_ranges":{"men_18_24":5895,"men_25_34":8835,"men_35_44":12923,"men_45_64":31025,"men_65+":18506,"women_18_24":5525,"women_25_34":8477,"women_35_44":12263,"women_45_64":30823,"women_65+":22057},"medium_u":94023,"medium_r":62306,"county":{"id":"1","nce":"1","code":"AB","name":"ALBA","updated_at":"2016-03-09 12:15:24"},"county_id":1},{"initial_count_lp":379299,"initial_count_lc":0,"precincts_count":440,"LP":157973,"LS":21112,"LSC":0,"UM":2586,"LT":181671,"presence":47.8965,"age_ranges":{"men_18_24":6923,"men_25_34":10977,"men_35_44":16330,"men_45_64":36795,"men_65+":18792,"women_18_24":6377,"women_25_34":10680,"women_35_44":15326,"women_45_64":36188,"women_65+":23283},"medium_u":104378,"medium_r":77293,"county":{"id":"2","nce":"2","code":"AR","name":"ARAD","updated_at":"2016-03-09 12:15:24"},"county_id":2},{"initial_count_lp":508415,"initial_count_lc":0,"precincts_count":527,"LP":242949,"LS":38082,"LSC":0,"UM":2009,"LT":283040,"presence":55.6711,"age_ranges":{"men_18_24":9588,"men_25_34":15206,"men_35_44":24042,"men_45_64":58654,"men_65+":29563,"women_18_24":9135,"women_25_34":15744,"women_35_44":23579,"women_45_64":60902,"women_65+":36627},"medium_u":135640,"medium_r":147400,"county":{"id":"3","nce":"3","code":"AG","name":"ARGEŞ","updated_at":"2016-03-09 12:15:24"},"county_id":3},{"initial_count_lp":586835,"initial_count_lc":0,"precincts_count":640,"LP":226667,"LS":27244,"LSC":0,"UM":2015,"LT":255926,"presence":43.6112,"age_ranges":{"men_18_24":8616,"men_25_34":11984,"men_35_44":19584,"men_45_64":51064,"men_65+":30226,"women_18_24":8714,"women_25_34":13501,"women_35_44":20302,"women_45_64":53670,"women_65+":38265},"medium_u":124427,"medium_r":131499,"county":{"id":"4","nce":"4","code":"BC","name":"BACĂU","updated_at":"2016-03-09 12:15:24"},"county_id":4},{"initial_count_lp":496810,"initial_count_lc":0,"precincts_count":660,"LP":218823,"LS":34119,"LSC":0,"UM":3880,"LT":256822,"presence":51.6942,"age_ranges":{"men_18_24":10508,"men_25_34":16292,"men_35_44":22841,"men_45_64":49273,"men_65+":25246,"women_18_24":10734,"women_25_34":16460,"women_35_44":22671,"women_45_64":50232,"women_65+":32565},"medium_u":129858,"medium_r":126964,"county":{"id":"5","nce":"5","code":"BH","name":"BIHOR","updated_at":"2016-03-09 12:15:24"},"county_id":5},{"initial_count_lp":260263,"initial_count_lc":0,"precincts_count":314,"LP":105819,"LS":12154,"LSC":0,"UM":1512,"LT":119485,"presence":45.9093,"age_ranges":{"men_18_24":4624,"men_25_34":6784,"men_35_44":10048,"men_45_64":23191,"men_65+":13649,"women_18_24":4897,"women_25_34":7259,"women_35_44":9905,"women_45_64":23918,"women_65+":15210},"medium_u":52211,"medium_r":67274,"county":{"id":"6","nce":"6","code":"BN","name":"BISTRIŢA-NĂSĂUD","updated_at":"2016-03-09 12:15:24"},"county_id":6},{"initial_count_lp":374762,"initial_count_lc":0,"precincts_count":434,"LP":133575,"LS":15064,"LSC":0,"UM":1800,"LT":150439,"presence":40.1425,"age_ranges":{"men_18_24":5383,"men_25_34":6937,"men_35_44":11162,"men_45_64":30698,"men_65+":17202,"women_18_24":5759,"women_25_34":8409,"women_35_44":12151,"women_45_64":32131,"women_65+":20607},"medium_u":68505,"medium_r":81934,"county":{"id":"7","nce":"7","code":"BT","name":"BOTOŞANI","updated_at":"2016-03-09 12:15:24"},"county_id":7},{"initial_count_lp":524688,"initial_count_lc":0,"precincts_count":468,"LP":243774,"LS":46697,"LSC":0,"UM":1712,"LT":292183,"presence":55.687,"age_ranges":{"men_18_24":11621,"men_25_34":17970,"men_35_44":26980,"men_45_64":50227,"men_65+":31337,"women_18_24":11974,"women_25_34":18776,"women_35_44":26916,"women_45_64":54526,"women_65+":41856},"medium_u":213133,"medium_r":79050,"county":{"id":"8","nce":"8","code":"BV","name":"BRAŞOV","updated_at":"2016-03-09 12:15:24"},"county_id":8},{"initial_count_lp":269308,"initial_count_lc":0,"precincts_count":284,"LP":115501,"LS":10355,"LSC":0,"UM":1103,"LT":126959,"presence":47.1427,"age_ranges":{"men_18_24":3783,"men_25_34":5159,"men_35_44":9373,"men_45_64":26700,"men_65+":15342,"women_18_24":3619,"women_25_34":5388,"women_35_44":9445,"women_45_64":28425,"women_65+":19725},"medium_u":85128,"medium_r":41831,"county":{"id":"9","nce":"9","code":"BR","name":"BRĂILA","updated_at":"2016-03-09 12:15:24"},"county_id":9},{"initial_count_lp":362983,"initial_count_lc":0,"precincts_count":425,"LP":156490,"LS":24319,"LSC":0,"UM":1385,"LT":182194,"presence":50.1935,"age_ranges":{"men_18_24":6046,"men_25_34":8196,"men_35_44":13487,"men_45_64":37400,"men_65+":23032,"women_18_24":5815,"women_25_34":8642,"women_35_44":13635,"women_45_64":38037,"women_65+":27904},"medium_u":75074,"medium_r":107120,"county":{"id":"10","nce":"10","code":"BZ","name":"BUZĂU","updated_at":"2016-03-09 12:15:24"},"county_id":10},{"initial_count_lp":252084,"initial_count_lc":0,"precincts_count":364,"LP":88206,"LS":14639,"LSC":0,"UM":1065,"LT":103910,"presence":41.2204,"age_ranges":{"men_18_24":3644,"men_25_34":4983,"men_35_44":7903,"men_45_64":21758,"men_65+":14043,"women_18_24":3473,"women_25_34":4833,"women_35_44":7170,"women_45_64":20248,"women_65+":15855},"medium_u":56216,"medium_r":47694,"county":{"id":"11","nce":"11","code":"CS","name":"CARAŞ-SEVERIN","updated_at":"2016-03-09 12:15:24"},"county_id":11},{"initial_count_lp":238114,"initial_count_lc":0,"precincts_count":235,"LP":96599,"LS":18414,"LSC":0,"UM":897,"LT":115910,"presence":48.6784,"age_ranges":{"men_18_24":4086,"men_25_34":5707,"men_35_44":9379,"men_45_64":24639,"men_65+":13242,"women_18_24":3878,"women_25_34":5969,"women_35_44":8984,"women_45_64":24208,"women_65+":15818},"medium_u":45089,"medium_r":70821,"county":{"id":"12","nce":"12","code":"CL","name":"CĂLĂRAŞI","updated_at":"2016-03-09 12:15:24"},"county_id":12},{"initial_count_lp":616314,"initial_count_lc":0,"precincts_count":674,"LP":291844,"LS":88653,"LSC":0,"UM":4086,"LT":384583,"presence":62.4005,"age_ranges":{"men_18_24":20288,"men_25_34":29368,"men_35_44":36048,"men_45_64":62132,"men_65+":35669,"women_18_24":23556,"women_25_34":31292,"women_35_44":36149,"women_45_64":65059,"women_65+":45022},"medium_u":250643,"medium_r":133940,"county":{"id":"13","nce":"13","code":"CJ","name":"CLUJ","updated_at":"2016-03-09 12:15:24"},"county_id":13},{"initial_count_lp":612441,"initial_count_lc":0,"precincts_count":563,"LP":281197,"LS":42108,"LSC":0,"UM":2140,"LT":325445,"presence":53.139,"age_ranges":{"men_18_24":11838,"men_25_34":15735,"men_35_44":26846,"men_45_64":60390,"men_65+":35665,"women_18_24":11990,"women_25_34":18203,"women_35_44":30322,"women_45_64":68027,"women_65+":46429},"medium_u":229279,"medium_r":96166,"county":{"id":"14","nce":"14","code":"CT","name":"CONSTANŢA","updated_at":"2016-03-09 12:15:24"},"county_id":14},{"initial_count_lp":178849,"initial_count_lc":0,"precincts_count":214,"LP":80575,"LS":9188,"LSC":0,"UM":2327,"LT":92090,"presence":51.4904,"age_ranges":{"men_18_24":3419,"men_25_34":4571,"men_35_44":7509,"men_45_64":16598,"men_65+":10711,"women_18_24":3396,"women_25_34":5110,"women_35_44":7886,"women_45_64":18695,"women_65+":14195},"medium_u":46498,"medium_r":45592,"county":{"id":"15","nce":"15","code":"CV","name":"COVASNA","updated_at":"2016-03-09 12:15:24"},"county_id":15},{"initial_count_lp":415034,"initial_count_lc":0,"precincts_count":434,"LP":183070,"LS":28378,"LSC":0,"UM":1544,"LT":212992,"presence":51.3192,"age_ranges":{"men_18_24":7843,"men_25_34":11722,"men_35_44":17791,"men_45_64":43562,"men_65+":23039,"women_18_24":7703,"women_25_34":11771,"women_35_44":17341,"women_45_64":43581,"women_65+":28639},"medium_u":66168,"medium_r":146824,"county":{"id":"16","nce":"16","code":"DB","name":"DÂMBOVIŢA","updated_at":"2016-03-09 12:15:24"},"county_id":16},{"initial_count_lp":549255,"initial_count_lc":0,"precincts_count":534,"LP":220151,"LS":35314,"LSC":0,"UM":4421,"LT":259886,"presence":47.3161,"age_ranges":{"men_18_24":8763,"men_25_34":14048,"men_35_44":21153,"men_45_64":52484,"men_65+":29673,"women_18_24":8897,"women_25_34":14826,"women_35_44":21303,"women_45_64":53405,"women_65+":35334},"medium_u":146143,"medium_r":113743,"county":{"id":"17","nce":"17","code":"DJ","name":"DOLJ","updated_at":"2016-03-09 12:15:24"},"county_id":17},{"initial_count_lp":520419,"initial_count_lc":0,"precincts_count":438,"LP":200783,"LS":20774,"LSC":0,"UM":1755,"LT":223312,"presence":42.91,"age_ranges":{"men_18_24":7115,"men_25_34":10081,"men_35_44":16532,"men_45_64":45773,"men_65+":26429,"women_18_24":7238,"women_25_34":10846,"women_35_44":17509,"women_45_64":47692,"women_65+":34097},"medium_u":129829,"medium_r":93483,"county":{"id":"18","nce":"18","code":"GL","name":"GALAŢI","updated_at":"2016-03-09 12:15:24"},"county_id":18},{"initial_count_lp":212800,"initial_count_lc":0,"precincts_count":245,"LP":89690,"LS":25248,"LSC":0,"UM":3483,"LT":118421,"presence":55.649,"age_ranges":{"men_18_24":4495,"men_25_34":7279,"men_35_44":10622,"men_45_64":24557,"men_65+":12624,"women_18_24":4183,"women_25_34":6841,"women_35_44":9644,"women_45_64":23370,"women_65+":14806},"medium_u":32799,"medium_r":85622,"county":{"id":"19","nce":"19","code":"GR","name":"GIURGIU","updated_at":"2016-03-09 12:15:24"},"county_id":19},{"initial_count_lp":286650,"initial_count_lc":0,"precincts_count":334,"LP":120623,"LS":20018,"LSC":0,"UM":1183,"LT":141824,"presence":49.4764,"age_ranges":{"men_18_24":4482,"men_25_34":7252,"men_35_44":11711,"men_45_64":32366,"men_65+":15273,"women_18_24":4357,"women_25_34":7485,"women_35_44":11639,"women_45_64":31308,"women_65+":15951},"medium_u":64849,"medium_r":76975,"county":{"id":"20","nce":"20","code":"GJ","name":"GORJ","updated_at":"2016-03-09 12:15:24"},"county_id":20},{"initial_count_lp":263523,"initial_count_lc":0,"precincts_count":292,"LP":127264,"LS":12180,"LSC":0,"UM":3569,"LT":143013,"presence":54.2696,"age_ranges":{"men_18_24":5614,"men_25_34":7924,"men_35_44":12051,"men_45_64":26229,"men_65+":15537,"women_18_24":5574,"women_25_34":8524,"women_35_44":12577,"women_45_64":27842,"women_65+":21141},"medium_u":59623,"medium_r":83390,"county":{"id":"21","nce":"21","code":"HR","name":"HARGHITA","updated_at":"2016-03-09 12:15:24"},"county_id":21},{"initial_count_lp":362006,"initial_count_lc":0,"precincts_count":525,"LP":152436,"LS":19796,"LSC":0,"UM":2047,"LT":174279,"presence":48.1426,"age_ranges":{"men_18_24":5239,"men_25_34":8082,"men_35_44":13041,"men_45_64":38025,"men_65+":20388,"women_18_24":4908,"women_25_34":8013,"women_35_44":12564,"women_45_64":38451,"women_65+":25568},"medium_u":126527,"medium_r":47752,"county":{"id":"22","nce":"22","code":"HD","name":"HUNEDOARA","updated_at":"2016-03-09 12:15:24"},"county_id":22},{"initial_count_lp":219814,"initial_count_lc":0,"precincts_count":220,"LP":85711,"LS":14153,"LSC":0,"UM":960,"LT":100824,"presence":45.8679,"age_ranges":{"men_18_24":3458,"men_25_34":4875,"men_35_44":7337,"men_45_64":21812,"men_65+":11774,"women_18_24":3430,"women_25_34":4855,"women_35_44":7345,"women_45_64":21776,"women_65+":14162},"medium_u":47551,"medium_r":53273,"county":{"id":"23","nce":"23","code":"IL","name":"IALOMIŢA","updated_at":"2016-03-09 12:15:24"},"county_id":23},{"initial_count_lp":810595,"initial_count_lc":0,"precincts_count":784,"LP":300044,"LS":61159,"LSC":0,"UM":3290,"LT":364493,"presence":44.9661,"age_ranges":{"men_18_24":18334,"men_25_34":24602,"men_35_44":32492,"men_45_64":63661,"men_65+":34073,"women_18_24":21755,"women_25_34":27321,"women_35_44":33167,"women_45_64":65231,"women_65+":43857},"medium_u":189348,"medium_r":175145,"county":{"id":"24","nce":"24","code":"IS","name":"IAŞI","updated_at":"2016-03-09 12:15:24"},"county_id":24},{"initial_count_lp":433057,"initial_count_lc":0,"precincts_count":296,"LP":216051,"LS":90772,"LSC":0,"UM":2213,"LT":309036,"presence":71.3615,"age_ranges":{"men_18_24":12238,"men_25_34":22242,"men_35_44":36869,"men_45_64":56734,"men_65+":20226,"women_18_24":12431,"women_25_34":24372,"women_35_44":38445,"women_45_64":58322,"women_65+":27157},"medium_u":139664,"medium_r":169372,"county":{"id":"25","nce":"25","code":"IF","name":"ILFOV","updated_at":"2016-03-09 12:15:24"},"county_id":25},{"initial_count_lp":419547,"initial_count_lc":0,"precincts_count":444,"LP":161907,"LS":18502,"LSC":0,"UM":1799,"LT":182208,"presence":43.4297,"age_ranges":{"men_18_24":6534,"men_25_34":10354,"men_35_44":15271,"men_45_64":36284,"men_65+":19656,"women_18_24":6565,"women_25_34":10883,"women_35_44":15429,"women_45_64":37373,"women_65+":23859},"medium_u":109345,"medium_r":72863,"county":{"id":"26","nce":"26","code":"MM","name":"MARAMUREŞ","updated_at":"2016-03-09 12:15:24"},"county_id":26},{"initial_count_lp":220555,"initial_count_lc":0,"precincts_count":290,"LP":82517,"LS":18516,"LSC":0,"UM":2458,"LT":103491,"presence":46.923,"age_ranges":{"men_18_24":2987,"men_25_34":4586,"men_35_44":7325,"men_45_64":22724,"men_65+":13230,"women_18_24":2831,"women_25_34":4707,"women_35_44":7463,"women_45_64":22432,"women_65+":15206},"medium_u":45270,"medium_r":58221,"county":{"id":"27","nce":"27","code":"MH","name":"MEHEDINŢI","updated_at":"2016-03-09 12:15:24"},"county_id":27},{"initial_count_lp":468694,"initial_count_lc":0,"precincts_count":572,"LP":200827,"LS":28494,"LSC":0,"UM":3696,"LT":233017,"presence":49.7162,"age_ranges":{"men_18_24":9630,"men_25_34":12993,"men_35_44":17901,"men_45_64":44693,"men_65+":26052,"women_18_24":9921,"women_25_34":13787,"women_35_44":18432,"women_45_64":45887,"women_65+":33721},"medium_u":125963,"medium_r":107054,"county":{"id":"28","nce":"28","code":"MS","name":"MUREŞ","updated_at":"2016-03-09 12:15:24"},"county_id":28},{"initial_count_lp":452890,"initial_count_lc":0,"precincts_count":490,"LP":180936,"LS":21088,"LSC":0,"UM":1095,"LT":203119,"presence":44.8495,"age_ranges":{"men_18_24":6546,"men_25_34":9342,"men_35_44":15032,"men_45_64":41040,"men_65+":24850,"women_18_24":6497,"women_25_34":10424,"women_35_44":16011,"women_45_64":42543,"women_65+":30834},"medium_u":80422,"medium_r":122697,"county":{"id":"29","nce":"29","code":"NT","name":"NEAMŢ","updated_at":"2016-03-09 12:15:24"},"county_id":29},{"initial_count_lp":344810,"initial_count_lc":0,"precincts_count":381,"LP":141024,"LS":24854,"LSC":0,"UM":2669,"LT":168547,"presence":48.8811,"age_ranges":{"men_18_24":5176,"men_25_34":8505,"men_35_44":12976,"men_45_64":37026,"men_65+":20407,"women_18_24":5013,"women_25_34":8697,"women_35_44":12319,"women_45_64":35389,"women_65+":23039},"medium_u":69319,"medium_r":99228,"county":{"id":"30","nce":"30","code":"OT","name":"OLT","updated_at":"2016-03-09 12:15:24"},"county_id":30},{"initial_count_lp":630657,"initial_count_lc":0,"precincts_count":624,"LP":297116,"LS":44813,"LSC":0,"UM":2759,"LT":344688,"presence":54.6554,"age_ranges":{"men_18_24":12013,"men_25_34":17011,"men_35_44":27317,"men_45_64":69223,"men_65+":37811,"women_18_24":11962,"women_25_34":17989,"women_35_44":28488,"women_45_64":74385,"women_65+":48489},"medium_u":175835,"medium_r":168853,"county":{"id":"31","nce":"31","code":"PH","name":"PRAHOVA","updated_at":"2016-03-09 12:15:24"},"county_id":31},{"initial_count_lp":309998,"initial_count_lc":0,"precincts_count":340,"LP":112789,"LS":11594,"LSC":0,"UM":1896,"LT":126279,"presence":40.7354,"age_ranges":{"men_18_24":4543,"men_25_34":6739,"men_35_44":10560,"men_45_64":25575,"men_65+":12545,"women_18_24":4430,"women_25_34":6936,"women_35_44":10887,"women_45_64":26981,"women_65+":17083},"medium_u":64183,"medium_r":62096,"county":{"id":"32","nce":"32","code":"SM","name":"SATU MARE","updated_at":"2016-03-09 12:15:24"},"county_id":32},{"initial_count_lp":191164,"initial_count_lc":0,"precincts_count":312,"LP":82268,"LS":14061,"LSC":0,"UM":1437,"LT":97766,"presence":51.1425,"age_ranges":{"men_18_24":3646,"men_25_34":5558,"men_35_44":7931,"men_45_64":19684,"men_65+":10880,"women_18_24":3703,"women_25_34":5534,"women_35_44":7661,"women_45_64":19649,"women_65+":13520},"medium_u":39691,"medium_r":58075,"county":{"id":"33","nce":"33","code":"SJ","name":"SĂLAJ","updated_at":"2016-03-09 12:15:24"},"county_id":33},{"initial_count_lp":382663,"initial_count_lc":0,"precincts_count":381,"LP":167009,"LS":28918,"LSC":0,"UM":1096,"LT":197023,"presence":51.4873,"age_ranges":{"men_18_24":7634,"men_25_34":12561,"men_35_44":18289,"men_45_64":35183,"men_65+":20205,"women_18_24":8181,"women_25_34":13268,"women_35_44":18057,"women_45_64":36705,"women_65+":26940},"medium_u":138088,"medium_r":58935,"county":{"id":"34","nce":"34","code":"SB","name":"SIBIU","updated_at":"2016-03-09 12:15:24"},"county_id":34},{"initial_count_lp":608321,"initial_count_lc":0,"precincts_count":564,"LP":242946,"LS":26753,"LSC":0,"UM":975,"LT":270674,"presence":44.4953,"age_ranges":{"men_18_24":10525,"men_25_34":14879,"men_35_44":21603,"men_45_64":52900,"men_65+":29673,"women_18_24":11050,"women_25_34":17205,"women_35_44":23235,"women_45_64":54963,"women_65+":34641},"medium_u":119358,"medium_r":151316,"county":{"id":"35","nce":"35","code":"SV","name":"SUCEAVA","updated_at":"2016-03-09 12:15:24"},"county_id":35},{"initial_count_lp":282274,"initial_count_lc":0,"precincts_count":334,"LP":106957,"LS":22262,"LSC":0,"UM":3231,"LT":132450,"presence":46.9225,"age_ranges":{"men_18_24":3851,"men_25_34":5943,"men_35_44":8869,"men_45_64":28330,"men_65+":19177,"women_18_24":3583,"women_25_34":5760,"women_35_44":8022,"women_45_64":26493,"women_65+":22422},"medium_u":42784,"medium_r":89666,"county":{"id":"36","nce":"36","code":"TR","name":"TELEORMAN","updated_at":"2016-03-09 12:15:24"},"county_id":36},{"initial_count_lp":631449,"initial_count_lc":0,"precincts_count":619,"LP":268509,"LS":64250,"LSC":0,"UM":2568,"LT":335327,"presence":53.1044,"age_ranges":{"men_18_24":14930,"men_25_34":25112,"men_35_44":33835,"men_45_64":59694,"men_65+":30220,"women_18_24":15933,"women_25_34":25174,"women_35_44":32219,"women_45_64":59311,"women_65+":38899},"medium_u":188003,"medium_r":147324,"county":{"id":"37","nce":"37","code":"TM","name":"TIMIŞ","updated_at":"2016-03-09 12:15:24"},"county_id":37},{"initial_count_lp":184226,"initial_count_lc":0,"precincts_count":205,"LP":73959,"LS":13026,"LSC":0,"UM":1095,"LT":88080,"presence":47.8108,"age_ranges":{"men_18_24":2594,"men_25_34":3617,"men_35_44":7002,"men_45_64":18740,"men_65+":11007,"women_18_24":2346,"women_25_34":3744,"women_35_44":6829,"women_45_64":19306,"women_65+":12895},"medium_u":43739,"medium_r":44341,"county":{"id":"38","nce":"38","code":"TL","name":"TULCEA","updated_at":"2016-03-09 12:15:24"},"county_id":38},{"initial_count_lp":426400,"initial_count_lc":0,"precincts_count":552,"LP":127743,"LS":16762,"LSC":0,"UM":1657,"LT":146162,"presence":34.2781,"age_ranges":{"men_18_24":5016,"men_25_34":6199,"men_35_44":10161,"men_45_64":30755,"men_65+":18250,"women_18_24":5497,"women_25_34":7284,"women_35_44":10482,"women_45_64":31061,"women_65+":21457},"medium_u":66425,"medium_r":79737,"county":{"id":"39","nce":"39","code":"VS","name":"VASLUI","updated_at":"2016-03-09 12:15:24"},"county_id":39},{"initial_count_lp":313180,"initial_count_lc":0,"precincts_count":434,"LP":134376,"LS":25592,"LSC":0,"UM":990,"LT":160958,"presence":51.3947,"age_ranges":{"men_18_24":4699,"men_25_34":7109,"men_35_44":11870,"men_45_64":33851,"men_65+":20441,"women_18_24":4640,"women_25_34":7445,"women_35_44":12161,"women_45_64":34986,"women_65+":23756},"medium_u":77538,"medium_r":83420,"county":{"id":"40","nce":"40","code":"VL","name":"VÂLCEA","updated_at":"2016-03-09 12:15:24"},"county_id":40},{"initial_count_lp":303376,"initial_count_lc":0,"precincts_count":364,"LP":122372,"LS":17921,"LSC":0,"UM":1289,"LT":141582,"presence":46.6688,"age_ranges":{"men_18_24":4530,"men_25_34":6205,"men_35_44":10817,"men_45_64":28290,"men_65+":18233,"women_18_24":4392,"women_25_34":6670,"women_35_44":10697,"women_45_64":28986,"women_65+":22762},"medium_u":54178,"medium_r":87404,"county":{"id":"41","nce":"41","code":"VN","name":"VRANCEA","updated_at":"2016-03-09 12:15:24"},"county_id":41},{"initial_count_lp":1781554,"initial_count_lc":0,"precincts_count":1289,"LP":818743,"LS":155620,"LSC":0,"UM":7141,"LT":981504,"presence":55.0926,"age_ranges":{"men_18_24":44473,"men_25_34":69186,"men_35_44":95595,"men_45_64":154267,"men_65+":78610,"women_18_24":48321,"women_25_34":76165,"women_35_44":103545,"women_45_64":185556,"women_65+":125786},"medium_u":981504,"medium_r":0,"county":{"id":"42","nce":"42","code":"B","name":"MUNICIPIUL BUCUREŞTI","updated_at":"2016-03-09 12:15:24"},"county_id":42},{"initial_count_lp":0,"initial_count_lc":0,"precincts_count":966,"LP":0,"LS":1509544,"LSC":3139,"UM":0,"LT":1512683,"presence":0,"age_ranges":{"men_18_24":65688,"men_25_34":155879,"men_35_44":243615,"men_45_64":317775,"men_65+":33242,"women_18_24":57498,"women_25_34":132317,"women_35_44":195499,"women_45_64":266017,"women_65+":45153},"medium_u":1512683,"medium_r":0,"county":{"id":"43","nce":"43","code":"SR","name":"STRĂINĂTATE","updated_at":"2016-10-03 11:57:18"},"county_id":43}]}