{"county":[{"initial_count_lp":302142,"initial_count_lc":0,"precincts_count":440,"LP":136949,"LS":19790,"LSC":0,"UM":2166,"LT":158905,"presence":52.5928,"age_ranges":{"men_18_24":6019,"men_25_34":9042,"men_35_44":13166,"men_45_64":31540,"men_65+":18676,"women_18_24":5641,"women_25_34":8688,"women_35_44":12524,"women_45_64":31362,"women_65+":22247},"medium_u":95543,"medium_r":63362,"county":{"id":"1","nce":"1","code":"AB","name":"ALBA","updated_at":"2016-03-09 12:15:24"},"county_id":1},{"initial_count_lp":379299,"initial_count_lc":0,"precincts_count":440,"LP":160403,"LS":21430,"LSC":0,"UM":2596,"LT":184429,"presence":48.6236,"age_ranges":{"men_18_24":7042,"men_25_34":11197,"men_35_44":16595,"men_45_64":37346,"men_65+":18949,"women_18_24":6512,"women_25_34":10893,"women_35_44":15607,"women_45_64":36788,"women_65+":23500},"medium_u":105767,"medium_r":78662,"county":{"id":"2","nce":"2","code":"AR","name":"ARAD","updated_at":"2016-03-09 12:15:24"},"county_id":2},{"initial_count_lp":508415,"initial_count_lc":0,"precincts_count":527,"LP":245611,"LS":38571,"LSC":0,"UM":2026,"LT":286208,"presence":56.2942,"age_ranges":{"men_18_24":9733,"men_25_34":15411,"men_35_44":24393,"men_45_64":59267,"men_65+":29748,"women_18_24":9275,"women_25_34":16002,"women_35_44":23939,"women_45_64":61587,"women_65+":36853},"medium_u":137136,"medium_r":149072,"county":{"id":"3","nce":"3","code":"AG","name":"ARGEŞ","updated_at":"2016-03-09 12:15:24"},"county_id":3},{"initial_count_lp":586835,"initial_count_lc":0,"precincts_count":640,"LP":228856,"LS":27541,"LSC":0,"UM":2015,"LT":258412,"presence":44.0349,"age_ranges":{"men_18_24":8738,"men_25_34":12138,"men_35_44":19814,"men_45_64":51576,"men_65+":30379,"women_18_24":8856,"women_25_34":13672,"women_35_44":20581,"women_45_64":54216,"women_65+":38442},"medium_u":125682,"medium_r":132730,"county":{"id":"4","nce":"4","code":"BC","name":"BACĂU","updated_at":"2016-03-09 12:15:24"},"county_id":4},{"initial_count_lp":496810,"initial_count_lc":0,"precincts_count":660,"LP":222171,"LS":34685,"LSC":0,"UM":3922,"LT":260778,"presence":52.4905,"age_ranges":{"men_18_24":10697,"men_25_34":16623,"men_35_44":23254,"men_45_64":50001,"men_65+":25446,"women_18_24":10994,"women_25_34":16821,"women_35_44":23073,"women_45_64":51051,"women_65+":32818},"medium_u":131778,"medium_r":129000,"county":{"id":"5","nce":"5","code":"BH","name":"BIHOR","updated_at":"2016-03-09 12:15:24"},"county_id":5},{"initial_count_lp":260263,"initial_count_lc":0,"precincts_count":314,"LP":107285,"LS":12321,"LSC":0,"UM":1513,"LT":121119,"presence":46.5372,"age_ranges":{"men_18_24":4700,"men_25_34":6914,"men_35_44":10210,"men_45_64":23510,"men_65+":13727,"women_18_24":4988,"women_25_34":7408,"women_35_44":10085,"women_45_64":24255,"women_65+":15322},"medium_u":52861,"medium_r":68258,"county":{"id":"6","nce":"6","code":"BN","name":"BISTRIŢA-NĂSĂUD","updated_at":"2016-03-09 12:15:24"},"county_id":6},{"initial_count_lp":374762,"initial_count_lc":0,"precincts_count":434,"LP":134903,"LS":15234,"LSC":0,"UM":1801,"LT":151938,"presence":40.5425,"age_ranges":{"men_18_24":5469,"men_25_34":7038,"men_35_44":11296,"men_45_64":31024,"men_65+":17287,"women_18_24":5837,"women_25_34":8520,"women_35_44":12310,"women_45_64":32467,"women_65+":20690},"medium_u":69287,"medium_r":82651,"county":{"id":"7","nce":"7","code":"BT","name":"BOTOŞANI","updated_at":"2016-03-09 12:15:24"},"county_id":7},{"initial_count_lp":524688,"initial_count_lc":0,"precincts_count":468,"LP":246315,"LS":47326,"LSC":0,"UM":1712,"LT":295353,"presence":56.2912,"age_ranges":{"men_18_24":11848,"men_25_34":18253,"men_35_44":27316,"men_45_64":50713,"men_65+":31484,"women_18_24":12186,"women_25_34":19081,"women_35_44":27314,"women_45_64":55120,"women_65+":42038},"medium_u":215241,"medium_r":80112,"county":{"id":"8","nce":"8","code":"BV","name":"BRAŞOV","updated_at":"2016-03-09 12:15:24"},"county_id":8},{"initial_count_lp":269308,"initial_count_lc":0,"precincts_count":284,"LP":116820,"LS":10484,"LSC":0,"UM":1103,"LT":128407,"presence":47.6804,"age_ranges":{"men_18_24":3826,"men_25_34":5253,"men_35_44":9504,"men_45_64":27053,"men_65+":15432,"women_18_24":3664,"women_25_34":5468,"women_35_44":9600,"women_45_64":28787,"women_65+":19820},"medium_u":86015,"medium_r":42392,"county":{"id":"9","nce":"9","code":"BR","name":"BRĂILA","updated_at":"2016-03-09 12:15:24"},"county_id":9},{"initial_count_lp":362983,"initial_count_lc":0,"precincts_count":425,"LP":158651,"LS":24656,"LSC":0,"UM":1385,"LT":184692,"presence":50.8817,"age_ranges":{"men_18_24":6167,"men_25_34":8393,"men_35_44":13732,"men_45_64":37901,"men_65+":23181,"women_18_24":5936,"women_25_34":8831,"women_35_44":13895,"women_45_64":38559,"women_65+":28097},"medium_u":76107,"medium_r":108585,"county":{"id":"10","nce":"10","code":"BZ","name":"BUZĂU","updated_at":"2016-03-09 12:15:24"},"county_id":10},{"initial_count_lp":252084,"initial_count_lc":0,"precincts_count":364,"LP":89517,"LS":14855,"LSC":0,"UM":1065,"LT":105437,"presence":41.8261,"age_ranges":{"men_18_24":3698,"men_25_34":5071,"men_35_44":8053,"men_45_64":22094,"men_65+":14163,"women_18_24":3529,"women_25_34":4934,"women_35_44":7322,"women_45_64":20573,"women_65+":16000},"medium_u":56920,"medium_r":48517,"county":{"id":"11","nce":"11","code":"CS","name":"CARAŞ-SEVERIN","updated_at":"2016-03-09 12:15:24"},"county_id":11},{"initial_count_lp":238114,"initial_count_lc":0,"precincts_count":235,"LP":98240,"LS":18729,"LSC":0,"UM":897,"LT":117866,"presence":49.4998,"age_ranges":{"men_18_24":4197,"men_25_34":5847,"men_35_44":9580,"men_45_64":25036,"men_65+":13335,"women_18_24":4005,"women_25_34":6115,"women_35_44":9207,"women_45_64":24600,"women_65+":15944},"medium_u":45736,"medium_r":72130,"county":{"id":"12","nce":"12","code":"CL","name":"CĂLĂRAŞI","updated_at":"2016-03-09 12:15:24"},"county_id":12},{"initial_count_lp":616314,"initial_count_lc":0,"precincts_count":674,"LP":295895,"LS":90064,"LSC":0,"UM":4087,"LT":390046,"presence":63.2869,"age_ranges":{"men_18_24":20651,"men_25_34":29854,"men_35_44":36646,"men_45_64":62999,"men_65+":35926,"women_18_24":23979,"women_25_34":31859,"women_35_44":36785,"women_45_64":66001,"women_65+":45346},"medium_u":254063,"medium_r":135983,"county":{"id":"13","nce":"13","code":"CJ","name":"CLUJ","updated_at":"2016-03-09 12:15:24"},"county_id":13},{"initial_count_lp":612441,"initial_count_lc":0,"precincts_count":563,"LP":284843,"LS":42767,"LSC":0,"UM":2140,"LT":329750,"presence":53.8419,"age_ranges":{"men_18_24":12066,"men_25_34":16042,"men_35_44":27292,"men_45_64":61185,"men_65+":35879,"women_18_24":12243,"women_25_34":18548,"women_35_44":30820,"women_45_64":68952,"women_65+":46723},"medium_u":232154,"medium_r":97596,"county":{"id":"14","nce":"14","code":"CT","name":"CONSTANŢA","updated_at":"2016-03-09 12:15:24"},"county_id":14},{"initial_count_lp":178849,"initial_count_lc":0,"precincts_count":214,"LP":81555,"LS":9287,"LSC":0,"UM":2327,"LT":93169,"presence":52.0937,"age_ranges":{"men_18_24":3489,"men_25_34":4651,"men_35_44":7628,"men_45_64":16797,"men_65+":10766,"women_18_24":3455,"women_25_34":5204,"women_35_44":8010,"women_45_64":18928,"women_65+":14241},"medium_u":47027,"medium_r":46142,"county":{"id":"15","nce":"15","code":"CV","name":"COVASNA","updated_at":"2016-03-09 12:15:24"},"county_id":15},{"initial_count_lp":415034,"initial_count_lc":0,"precincts_count":434,"LP":185828,"LS":28821,"LSC":0,"UM":1562,"LT":216211,"presence":52.0948,"age_ranges":{"men_18_24":8016,"men_25_34":11964,"men_35_44":18144,"men_45_64":44197,"men_65+":23208,"women_18_24":7860,"women_25_34":12039,"women_35_44":17678,"women_45_64":44267,"women_65+":28838},"medium_u":67133,"medium_r":149078,"county":{"id":"16","nce":"16","code":"DB","name":"DÂMBOVIŢA","updated_at":"2016-03-09 12:15:24"},"county_id":16},{"initial_count_lp":549255,"initial_count_lc":0,"precincts_count":534,"LP":223680,"LS":35913,"LSC":0,"UM":4452,"LT":264045,"presence":48.0733,"age_ranges":{"men_18_24":8957,"men_25_34":14351,"men_35_44":21549,"men_45_64":53317,"men_65+":29923,"women_18_24":9091,"women_25_34":15179,"women_35_44":21754,"women_45_64":54270,"women_65+":35654},"medium_u":148264,"medium_r":115781,"county":{"id":"17","nce":"17","code":"DJ","name":"DOLJ","updated_at":"2016-03-09 12:15:24"},"county_id":17},{"initial_count_lp":520419,"initial_count_lc":0,"precincts_count":438,"LP":203326,"LS":21050,"LSC":0,"UM":1755,"LT":226131,"presence":43.4517,"age_ranges":{"men_18_24":7241,"men_25_34":10245,"men_35_44":16808,"men_45_64":46375,"men_65+":26589,"women_18_24":7379,"women_25_34":11045,"women_35_44":17812,"women_45_64":48347,"women_65+":34290},"medium_u":131288,"medium_r":94843,"county":{"id":"18","nce":"18","code":"GL","name":"GALAŢI","updated_at":"2016-03-09 12:15:24"},"county_id":18},{"initial_count_lp":212800,"initial_count_lc":0,"precincts_count":245,"LP":91424,"LS":25684,"LSC":0,"UM":3512,"LT":120620,"presence":56.6823,"age_ranges":{"men_18_24":4609,"men_25_34":7464,"men_35_44":10889,"men_45_64":24957,"men_65+":12738,"women_18_24":4305,"women_25_34":7034,"women_35_44":9873,"women_45_64":23804,"women_65+":14947},"medium_u":33353,"medium_r":87267,"county":{"id":"19","nce":"19","code":"GR","name":"GIURGIU","updated_at":"2016-03-09 12:15:24"},"county_id":19},{"initial_count_lp":286650,"initial_count_lc":0,"precincts_count":334,"LP":122259,"LS":20300,"LSC":0,"UM":1183,"LT":143742,"presence":50.1455,"age_ranges":{"men_18_24":4564,"men_25_34":7392,"men_35_44":11916,"men_45_64":32757,"men_65+":15373,"women_18_24":4460,"women_25_34":7659,"women_35_44":11846,"women_45_64":31715,"women_65+":16060},"medium_u":65756,"medium_r":77986,"county":{"id":"20","nce":"20","code":"GJ","name":"GORJ","updated_at":"2016-03-09 12:15:24"},"county_id":20},{"initial_count_lp":263523,"initial_count_lc":0,"precincts_count":292,"LP":128737,"LS":12350,"LSC":0,"UM":3628,"LT":144715,"presence":54.9155,"age_ranges":{"men_18_24":5696,"men_25_34":8045,"men_35_44":12216,"men_45_64":26539,"men_65+":15627,"women_18_24":5660,"women_25_34":8679,"women_35_44":12783,"women_45_64":28194,"women_65+":21276},"medium_u":60322,"medium_r":84393,"county":{"id":"21","nce":"21","code":"HR","name":"HARGHITA","updated_at":"2016-03-09 12:15:24"},"county_id":21},{"initial_count_lp":362006,"initial_count_lc":0,"precincts_count":525,"LP":154264,"LS":20088,"LSC":0,"UM":2047,"LT":176399,"presence":48.7282,"age_ranges":{"men_18_24":5327,"men_25_34":8240,"men_35_44":13252,"men_45_64":38450,"men_65+":20523,"women_18_24":5002,"women_25_34":8161,"women_35_44":12775,"women_45_64":38932,"women_65+":25737},"medium_u":127899,"medium_r":48500,"county":{"id":"22","nce":"22","code":"HD","name":"HUNEDOARA","updated_at":"2016-03-09 12:15:24"},"county_id":22},{"initial_count_lp":219814,"initial_count_lc":0,"precincts_count":220,"LP":86984,"LS":14364,"LSC":0,"UM":960,"LT":102308,"presence":46.543,"age_ranges":{"men_18_24":3511,"men_25_34":4981,"men_35_44":7484,"men_45_64":22156,"men_65+":11849,"women_18_24":3495,"women_25_34":4978,"women_35_44":7487,"women_45_64":22112,"women_65+":14255},"medium_u":48197,"medium_r":54111,"county":{"id":"23","nce":"23","code":"IL","name":"IALOMIŢA","updated_at":"2016-03-09 12:15:24"},"county_id":23},{"initial_count_lp":810595,"initial_count_lc":0,"precincts_count":784,"LP":303609,"LS":62086,"LSC":0,"UM":3290,"LT":368985,"presence":45.5203,"age_ranges":{"men_18_24":18648,"men_25_34":25022,"men_35_44":32969,"men_45_64":64393,"men_65+":34242,"women_18_24":22159,"women_25_34":27759,"women_35_44":33661,"women_45_64":66034,"women_65+":44098},"medium_u":191864,"medium_r":177121,"county":{"id":"24","nce":"24","code":"IS","name":"IAŞI","updated_at":"2016-03-09 12:15:24"},"county_id":24},{"initial_count_lp":433057,"initial_count_lc":0,"precincts_count":296,"LP":219114,"LS":92369,"LSC":0,"UM":2215,"LT":313698,"presence":72.438,"age_ranges":{"men_18_24":12485,"men_25_34":22672,"men_35_44":37511,"men_45_64":57465,"men_65+":20344,"women_18_24":12680,"women_25_34":24907,"women_35_44":39121,"women_45_64":59146,"women_65+":27367},"medium_u":141813,"medium_r":171885,"county":{"id":"25","nce":"25","code":"IF","name":"ILFOV","updated_at":"2016-03-09 12:15:24"},"county_id":25},{"initial_count_lp":419547,"initial_count_lc":0,"precincts_count":444,"LP":164101,"LS":18760,"LSC":0,"UM":1804,"LT":184665,"presence":44.0153,"age_ranges":{"men_18_24":6636,"men_25_34":10525,"men_35_44":15530,"men_45_64":36747,"men_65+":19790,"women_18_24":6691,"women_25_34":11101,"women_35_44":15707,"women_45_64":37895,"women_65+":24043},"medium_u":110720,"medium_r":73945,"county":{"id":"26","nce":"26","code":"MM","name":"MARAMUREŞ","updated_at":"2016-03-09 12:15:24"},"county_id":26},{"initial_count_lp":220555,"initial_count_lc":0,"precincts_count":290,"LP":83844,"LS":18760,"LSC":0,"UM":2458,"LT":105062,"presence":47.6353,"age_ranges":{"men_18_24":3050,"men_25_34":4671,"men_35_44":7468,"men_45_64":23074,"men_65+":13331,"women_18_24":2908,"women_25_34":4802,"women_35_44":7623,"women_45_64":22802,"women_65+":15333},"medium_u":46040,"medium_r":59022,"county":{"id":"27","nce":"27","code":"MH","name":"MEHEDINŢI","updated_at":"2016-03-09 12:15:24"},"county_id":27},{"initial_count_lp":468694,"initial_count_lc":0,"precincts_count":572,"LP":203722,"LS":28928,"LSC":0,"UM":3724,"LT":236374,"presence":50.4325,"age_ranges":{"men_18_24":9812,"men_25_34":13215,"men_35_44":18247,"men_45_64":45354,"men_65+":26215,"women_18_24":10124,"women_25_34":14052,"women_35_44":18806,"women_45_64":46577,"women_65+":33972},"medium_u":127691,"medium_r":108683,"county":{"id":"28","nce":"28","code":"MS","name":"MUREŞ","updated_at":"2016-03-09 12:15:24"},"county_id":28},{"initial_count_lp":452890,"initial_count_lc":0,"precincts_count":490,"LP":182744,"LS":21325,"LSC":0,"UM":1119,"LT":205188,"presence":45.3064,"age_ranges":{"men_18_24":6657,"men_25_34":9482,"men_35_44":15210,"men_45_64":41460,"men_65+":24967,"women_18_24":6581,"women_25_34":10584,"women_35_44":16233,"women_45_64":42995,"women_65+":31019},"medium_u":81299,"medium_r":123889,"county":{"id":"29","nce":"29","code":"NT","name":"NEAMŢ","updated_at":"2016-03-09 12:15:24"},"county_id":29},{"initial_count_lp":344810,"initial_count_lc":0,"precincts_count":381,"LP":143147,"LS":25193,"LSC":0,"UM":2669,"LT":171009,"presence":49.5951,"age_ranges":{"men_18_24":5295,"men_25_34":8664,"men_35_44":13205,"men_45_64":37578,"men_65+":20572,"women_18_24":5127,"women_25_34":8853,"women_35_44":12578,"women_45_64":35943,"women_65+":23194},"medium_u":70301,"medium_r":100708,"county":{"id":"30","nce":"30","code":"OT","name":"OLT","updated_at":"2016-03-09 12:15:24"},"county_id":30},{"initial_count_lp":630657,"initial_count_lc":0,"precincts_count":624,"LP":301019,"LS":45401,"LSC":0,"UM":2761,"LT":349181,"presence":55.3678,"age_ranges":{"men_18_24":12210,"men_25_34":17317,"men_35_44":27755,"men_45_64":70139,"men_65+":38056,"women_18_24":12189,"women_25_34":18329,"women_35_44":28990,"women_45_64":75371,"women_65+":48825},"medium_u":177932,"medium_r":171249,"county":{"id":"31","nce":"31","code":"PH","name":"PRAHOVA","updated_at":"2016-03-09 12:15:24"},"county_id":31},{"initial_count_lp":309998,"initial_count_lc":0,"precincts_count":340,"LP":114599,"LS":11777,"LSC":0,"UM":1896,"LT":128272,"presence":41.3783,"age_ranges":{"men_18_24":4629,"men_25_34":6875,"men_35_44":10742,"men_45_64":25999,"men_65+":12641,"women_18_24":4509,"women_25_34":7081,"women_35_44":11140,"women_45_64":27428,"women_65+":17228},"medium_u":65116,"medium_r":63156,"county":{"id":"32","nce":"32","code":"SM","name":"SATU MARE","updated_at":"2016-03-09 12:15:24"},"county_id":32},{"initial_count_lp":191164,"initial_count_lc":0,"precincts_count":312,"LP":83463,"LS":14275,"LSC":0,"UM":1437,"LT":99175,"presence":51.8795,"age_ranges":{"men_18_24":3699,"men_25_34":5662,"men_35_44":8078,"men_45_64":19957,"men_65+":10957,"women_18_24":3764,"women_25_34":5654,"women_35_44":7839,"women_45_64":19945,"women_65+":13620},"medium_u":40217,"medium_r":58958,"county":{"id":"33","nce":"33","code":"SJ","name":"SĂLAJ","updated_at":"2016-03-09 12:15:24"},"county_id":33},{"initial_count_lp":382663,"initial_count_lc":0,"precincts_count":381,"LP":169391,"LS":29408,"LSC":0,"UM":1096,"LT":199895,"presence":52.2379,"age_ranges":{"men_18_24":7779,"men_25_34":12808,"men_35_44":18597,"men_45_64":35675,"men_65+":20330,"women_18_24":8382,"women_25_34":13529,"women_35_44":18397,"women_45_64":37273,"women_65+":27125},"medium_u":139939,"medium_r":59956,"county":{"id":"34","nce":"34","code":"SB","name":"SIBIU","updated_at":"2016-03-09 12:15:24"},"county_id":34},{"initial_count_lp":608321,"initial_count_lc":0,"precincts_count":564,"LP":245471,"LS":27090,"LSC":0,"UM":988,"LT":273549,"presence":44.9679,"age_ranges":{"men_18_24":10678,"men_25_34":15078,"men_35_44":21880,"men_45_64":53431,"men_65+":29834,"women_18_24":11222,"women_25_34":17481,"women_35_44":23575,"women_45_64":55535,"women_65+":34835},"medium_u":120690,"medium_r":152859,"county":{"id":"35","nce":"35","code":"SV","name":"SUCEAVA","updated_at":"2016-03-09 12:15:24"},"county_id":35},{"initial_count_lp":282274,"initial_count_lc":0,"precincts_count":334,"LP":108842,"LS":22629,"LSC":0,"UM":3231,"LT":134702,"presence":47.7203,"age_ranges":{"men_18_24":3959,"men_25_34":6088,"men_35_44":9056,"men_45_64":28822,"men_65+":19354,"women_18_24":3672,"women_25_34":5889,"women_35_44":8227,"women_45_64":27003,"women_65+":22632},"medium_u":43512,"medium_r":91190,"county":{"id":"36","nce":"36","code":"TR","name":"TELEORMAN","updated_at":"2016-03-09 12:15:24"},"county_id":36},{"initial_count_lp":631449,"initial_count_lc":0,"precincts_count":619,"LP":272289,"LS":65342,"LSC":0,"UM":2568,"LT":340199,"presence":53.8759,"age_ranges":{"men_18_24":15205,"men_25_34":25486,"men_35_44":34387,"men_45_64":60544,"men_65+":30436,"women_18_24":16236,"women_25_34":25641,"women_35_44":32831,"women_45_64":60223,"women_65+":39210},"medium_u":190586,"medium_r":149613,"county":{"id":"37","nce":"37","code":"TM","name":"TIMIŞ","updated_at":"2016-03-09 12:15:24"},"county_id":37},{"initial_count_lp":184226,"initial_count_lc":0,"precincts_count":205,"LP":74924,"LS":13188,"LSC":0,"UM":1095,"LT":89207,"presence":48.4226,"age_ranges":{"men_18_24":2658,"men_25_34":3699,"men_35_44":7112,"men_45_64":18971,"men_65+":11075,"women_18_24":2407,"women_25_34":3819,"women_35_44":6935,"women_45_64":19553,"women_65+":12978},"medium_u":44246,"medium_r":44961,"county":{"id":"38","nce":"38","code":"TL","name":"TULCEA","updated_at":"2016-03-09 12:15:24"},"county_id":38},{"initial_count_lp":426400,"initial_count_lc":0,"precincts_count":552,"LP":129260,"LS":16988,"LSC":0,"UM":1664,"LT":147912,"presence":34.6886,"age_ranges":{"men_18_24":5102,"men_25_34":6316,"men_35_44":10311,"men_45_64":31146,"men_65+":18355,"women_18_24":5594,"women_25_34":7406,"women_35_44":10633,"women_45_64":31452,"women_65+":21597},"medium_u":67239,"medium_r":80673,"county":{"id":"39","nce":"39","code":"VS","name":"VASLUI","updated_at":"2016-03-09 12:15:24"},"county_id":39},{"initial_count_lp":313180,"initial_count_lc":0,"precincts_count":434,"LP":135982,"LS":25938,"LSC":0,"UM":991,"LT":162911,"presence":52.0183,"age_ranges":{"men_18_24":4785,"men_25_34":7236,"men_35_44":12068,"men_45_64":34231,"men_65+":20572,"women_18_24":4728,"women_25_34":7589,"women_35_44":12361,"women_45_64":35425,"women_65+":23916},"medium_u":78460,"medium_r":84451,"county":{"id":"40","nce":"40","code":"VL","name":"VÂLCEA","updated_at":"2016-03-09 12:15:24"},"county_id":40},{"initial_count_lp":303376,"initial_count_lc":0,"precincts_count":364,"LP":123697,"LS":18136,"LSC":0,"UM":1289,"LT":143122,"presence":47.1764,"age_ranges":{"men_18_24":4610,"men_25_34":6314,"men_35_44":10961,"men_45_64":28594,"men_65+":18332,"women_18_24":4461,"women_25_34":6770,"women_35_44":10856,"women_45_64":29330,"women_65+":22894},"medium_u":54826,"medium_r":88296,"county":{"id":"41","nce":"41","code":"VN","name":"VRANCEA","updated_at":"2016-03-09 12:15:24"},"county_id":41},{"initial_count_lp":1781554,"initial_count_lc":0,"precincts_count":1289,"LP":829313,"LS":158025,"LSC":0,"UM":7141,"LT":994479,"presence":55.8209,"age_ranges":{"men_18_24":45296,"men_25_34":70283,"men_35_44":97057,"men_45_64":156187,"men_65+":79152,"women_18_24":49222,"women_25_34":77466,"women_35_44":105193,"women_45_64":187981,"women_65+":126642},"medium_u":994479,"medium_r":0,"county":{"id":"42","nce":"42","code":"B","name":"MUNICIPIUL BUCUREŞTI","updated_at":"2016-03-09 12:15:24"},"county_id":42},{"initial_count_lp":0,"initial_count_lc":0,"precincts_count":966,"LP":0,"LS":1523607,"LSC":3139,"UM":0,"LT":1526746,"presence":0,"age_ranges":{"men_18_24":66459,"men_25_34":157568,"men_35_44":245968,"men_45_64":320116,"men_65+":33409,"women_18_24":58212,"women_25_34":133865,"women_35_44":197519,"women_45_64":268226,"women_65+":45404},"medium_u":1526746,"medium_r":0,"county":{"id":"43","nce":"43","code":"SR","name":"STRĂINĂTATE","updated_at":"2016-10-03 11:57:18"},"county_id":43}]}